[
  {
    "Version": "0.3",
    "Name": "",
    "Invulnerable": true,
    "SystemsOnline": true,
    "DoorsLocked": false,
    "HealthMultiplier": 0.5,
    "DockingControlsDisabled": true,
    "AirPressure": 0,
    "AirQuality": 0,
    "Structures": [
      {
        "StructureID": 0,
        "StructureType": "Generic_Debris_Corridor001",
        "Invulnerable": true,
        "SystemsOnline": true,
        "DoorsLocked": false,
        "HealthMultiplier": 0.5,
        "DockingControlsDisabled": true,
        "AirPressure": 0,
        "AirQuality": 0,
        "DockingPorts": [
          {
            "OrderID": 1,
            "DockedStructureID": 1,
            "Locked": true
          }
        ]
      },
      {
        "StructureID": 1,
        "StructureType": "SPM",
        "Invulnerable": true,
        "SystemsOnline": true,
        "DoorsLocked": false,
        "HealthMultiplier": 0.5,
        "DockingControlsDisabled": true,
        "AirPressure": 0,
        "AirQuality": 0,
        "DockingPorts": [
          {
            "OrderID": 1,
            "DockedStructureID": 0,
            "Locked": true
          },
          {
            "OrderID": 2,
            "DockedStructureID": 2,
            "Locked": true
          }
        ]
      },
      {
        "StructureID": 2,
        "StructureType": "CRM",
        "Invulnerable": true,
        "SystemsOnline": true,
        "DoorsLocked": false,
        "HealthMultiplier": 0.5,
        "DockingControlsDisabled": true,
        "AirPressure": 0,
        "AirQuality": 0,
        "DockingPorts": [
          {
            "OrderID": 1,
            "DockedStructureID": 1,
            "Locked": true
          },
          {
            "OrderID": 2,
            "DockedStructureID": 3,
            "Locked": true
          }
        ]
      },
      {
        "StructureID": 3,
        "StructureType": "Generic_Debris_JuncRoom002",
        "Invulnerable": true,
        "SystemsOnline": true,
        "DoorsLocked": false,
        "HealthMultiplier": 0.3,
        "DockingControlsDisabled": true,
        "AirPressure": 0,
        "AirQuality": 0,
        "DockingPorts": [
          {
            "OrderID": 1,
            "DockedStructureID": 2,
            "Locked": true
          },
          {
            "OrderID": 2,
            "DockedStructureID": 4,
            "Locked": true
          }
        ]
      },
      {
        "StructureID": 4,
        "StructureType": "Generic_Debris_Corridor001",
        "Invulnerable": true,
        "SystemsOnline": true,
        "DoorsLocked": false,
        "HealthMultiplier": 0.3,
        "DockingControlsDisabled": true,
        "AirPressure": 0,
        "AirQuality": 0,
        "DockingPorts": [
          {
            "OrderID": 1,
            "DockedStructureID": 3,
            "Locked": true
          }
        ]
      }
    ]
  }
]